{"trial_id": "14", "hyperparameters": {"space": [{"class_name": "Int", "config": {"name": "input_units", "default": null, "conditions": [], "min_value": 128, "max_value": 512, "step": 64, "sampling": "linear"}}, {"class_name": "Choice", "config": {"name": "input_activation", "default": "relu", "conditions": [], "values": ["relu", "tanh"], "ordered": false}}, {"class_name": "Float", "config": {"name": "l2_input", "default": 1e-05, "conditions": [], "min_value": 1e-05, "max_value": 0.01, "step": null, "sampling": "log"}}, {"class_name": "Boolean", "config": {"name": "batchnorm_input", "default": false, "conditions": []}}, {"class_name": "Float", "config": {"name": "dropout_input", "default": 0.1, "conditions": [], "min_value": 0.1, "max_value": 0.5, "step": 0.1, "sampling": "linear"}}, {"class_name": "Int", "config": {"name": "num_layers", "default": null, "conditions": [], "min_value": 2, "max_value": 5, "step": 1, "sampling": "linear"}}, {"class_name": "Int", "config": {"name": "units_0", "default": null, "conditions": [], "min_value": 64, "max_value": 512, "step": 64, "sampling": "linear"}}, {"class_name": "Choice", "config": {"name": "activation_0", "default": "relu", "conditions": [], "values": ["relu", "tanh"], "ordered": false}}, {"class_name": "Float", "config": {"name": "l2_0", "default": 1e-05, "conditions": [], "min_value": 1e-05, "max_value": 0.01, "step": null, "sampling": "log"}}, {"class_name": "Boolean", "config": {"name": "batchnorm_0", "default": false, "conditions": []}}, {"class_name": "Float", "config": {"name": "dropout_0", "default": 0.1, "conditions": [], "min_value": 0.1, "max_value": 0.6, "step": 0.1, "sampling": "linear"}}, {"class_name": "Int", "config": {"name": "units_1", "default": null, "conditions": [], "min_value": 64, "max_value": 512, "step": 64, "sampling": "linear"}}, {"class_name": "Choice", "config": {"name": "activation_1", "default": "relu", "conditions": [], "values": ["relu", "tanh"], "ordered": false}}, {"class_name": "Float", "config": {"name": "l2_1", "default": 1e-05, "conditions": [], "min_value": 1e-05, "max_value": 0.01, "step": null, "sampling": "log"}}, {"class_name": "Boolean", "config": {"name": "batchnorm_1", "default": false, "conditions": []}}, {"class_name": "Float", "config": {"name": "dropout_1", "default": 0.1, "conditions": [], "min_value": 0.1, "max_value": 0.6, "step": 0.1, "sampling": "linear"}}, {"class_name": "Choice", "config": {"name": "optimizer", "default": "adam", "conditions": [], "values": ["adam", "rmsprop", "sgd"], "ordered": false}}, {"class_name": "Float", "config": {"name": "learning_rate", "default": 0.0001, "conditions": [], "min_value": 0.0001, "max_value": 0.01, "step": null, "sampling": "log"}}, {"class_name": "Int", "config": {"name": "batch_size", "default": null, "conditions": [], "min_value": 32, "max_value": 128, "step": 32, "sampling": "linear"}}, {"class_name": "Int", "config": {"name": "units_2", "default": null, "conditions": [], "min_value": 64, "max_value": 512, "step": 64, "sampling": "linear"}}, {"class_name": "Choice", "config": {"name": "activation_2", "default": "relu", "conditions": [], "values": ["relu", "tanh"], "ordered": false}}, {"class_name": "Float", "config": {"name": "l2_2", "default": 1e-05, "conditions": [], "min_value": 1e-05, "max_value": 0.01, "step": null, "sampling": "log"}}, {"class_name": "Boolean", "config": {"name": "batchnorm_2", "default": false, "conditions": []}}, {"class_name": "Float", "config": {"name": "dropout_2", "default": 0.1, "conditions": [], "min_value": 0.1, "max_value": 0.6, "step": 0.1, "sampling": "linear"}}, {"class_name": "Int", "config": {"name": "units_3", "default": null, "conditions": [], "min_value": 64, "max_value": 512, "step": 64, "sampling": "linear"}}, {"class_name": "Choice", "config": {"name": "activation_3", "default": "relu", "conditions": [], "values": ["relu", "tanh"], "ordered": false}}, {"class_name": "Float", "config": {"name": "l2_3", "default": 1e-05, "conditions": [], "min_value": 1e-05, "max_value": 0.01, "step": null, "sampling": "log"}}, {"class_name": "Boolean", "config": {"name": "batchnorm_3", "default": false, "conditions": []}}, {"class_name": "Float", "config": {"name": "dropout_3", "default": 0.1, "conditions": [], "min_value": 0.1, "max_value": 0.6, "step": 0.1, "sampling": "linear"}}, {"class_name": "Int", "config": {"name": "units_4", "default": null, "conditions": [], "min_value": 64, "max_value": 512, "step": 64, "sampling": "linear"}}, {"class_name": "Choice", "config": {"name": "activation_4", "default": "relu", "conditions": [], "values": ["relu", "tanh"], "ordered": false}}, {"class_name": "Float", "config": {"name": "l2_4", "default": 1e-05, "conditions": [], "min_value": 1e-05, "max_value": 0.01, "step": null, "sampling": "log"}}, {"class_name": "Boolean", "config": {"name": "batchnorm_4", "default": false, "conditions": []}}, {"class_name": "Float", "config": {"name": "dropout_4", "default": 0.1, "conditions": [], "min_value": 0.1, "max_value": 0.6, "step": 0.1, "sampling": "linear"}}], "values": {"input_units": 512, "input_activation": "relu", "l2_input": 6.307559097452278e-05, "batchnorm_input": false, "dropout_input": 0.1, "num_layers": 5, "units_0": 320, "activation_0": "tanh", "l2_0": 0.0004180291875011648, "batchnorm_0": false, "dropout_0": 0.5, "units_1": 320, "activation_1": "relu", "l2_1": 0.0001574609026025296, "batchnorm_1": false, "dropout_1": 0.5, "optimizer": "sgd", "learning_rate": 0.0006397222967790205, "batch_size": 32, "units_2": 384, "activation_2": "tanh", "l2_2": 3.8544114857454415e-05, "batchnorm_2": true, "dropout_2": 0.5, "units_3": 256, "activation_3": "tanh", "l2_3": 2.58946845560749e-05, "batchnorm_3": false, "dropout_3": 0.30000000000000004, "units_4": 64, "activation_4": "tanh", "l2_4": 3.681879293275022e-05, "batchnorm_4": true, "dropout_4": 0.30000000000000004}}, "metrics": {"metrics": {"accuracy": {"direction": "max", "observations": [{"value": [0.7732544541358948], "step": 6}]}, "loss": {"direction": "min", "observations": [{"value": [0.9693577289581299], "step": 6}]}, "val_accuracy": {"direction": "max", "observations": [{"value": [0.8297067284584045], "step": 6}]}, "val_loss": {"direction": "min", "observations": [{"value": [0.8021261692047119], "step": 6}]}}}, "score": 0.8297067284584045, "best_step": 6, "status": "COMPLETED", "message": null}